{
  "dialogue": [
    {
      "scene": 0,
      "lines": [
        {
          "name": "드론",
          "line": "잘 정리 됐나요?"
        },
        {
          "name": "주인공",
          "line": "그래."
        }
      ]
    },
    {
      "scene": 1,
      "lines": [
        {
          "name": "주인공",
          "line": "덕분에 화려하게 날뛰었군."
        },
        {
          "name": "드론",
          "line": "사지 멀쩡하니 괜찮은 것 아닐까요?"
        }
      ]
    },
    {
      "scene": 2,
      "lines": [
        {
          "speed": 0.05,
          "name": "주인공",
          "line": "제대로 망쳤어."
        },
        {
          "name": "주인공",
          "line": "아주 제대로."
        },
        {
          "name": "주인공",
          "line": "*심한 욕설*"
        },
        {
          "name": "드론",
          "line": "벌집이라도 건드린 것 같네요."
        },
        {
          "name": "드론",
          "line": "대체 무슨 짓을 하고 다니신 겁니까?"
        },
        {
          "name": "주인공",
          "line": "잘 모르겠어."
        },
        {
          "name": "주인공",
          "line": "도망칠 경로가 있나?"
        },
        {
          "name": "드론",
          "line": "계산하지 않아도 알겠네요."
        },
        {
          "name": "드론",
          "line": "난장판을 쳐서 경찰까지 쫓아오고 있습니다."
        },
        {
          "name": "드론",
          "line": "둘을 동시에 상대할 수는 없어요."
        },
        {
          "name": "주인공",
          "line": "*한숨*"
        },
        {
          "name": "주인공",
          "line": "나도 알고 있어."
        },
        {
          "name": "주인공",
          "line": "혹시나 해서."
        },
        {
          "name": "주인공",
          "line": "가는데까지 가보는 수밖에 없나."
        },
        {
          "name": "드론",
          "line": ". . . "
        },
        {
          "name": "드론",
          "line": "길이 아예 없는 것은 아닙니다."
        },
        {
          "name": "주인공",
          "line": "들어나 보자."
        },
        {
          "name": "드론",
          "line": "제가 네트워크를 봉쇄할 때의 일입니다..."
        },
        {
          "speed": 0.01,
          "name": "드론",
          "line": "<size=30>여러기기의연결을끊는중요한작업이죠.예를들어냉장고의연결을끊는것은\n외부연결에의지하는여러기능들을일시적으로정지해야하기때문에생각보\n다굉장히까다로운일입니다.비슷한맥락에서요즘은정말아무거나다별이유\n도없이네트워크에연결되어있기때문에쓸데없는수고를들여야하는귀찮은\n작업으로변모하게되었다고볼수있을것같습니다.그과정에서당연하게도pc\n의기능도유지해야했기때문에내부네트워크기록을살펴보게되었는데그내\n용은010100010010110(반복)...</size>"
        },
        {
          "name": "주인공",
          "line": "<size=100><b>*한숨*</b></size>"
        },
        {
          "name": "주인공",
          "line": "여긴 한동안 안전한가봐?"
        },
        {
          "name": "드론",
          "line": "그렇습니다."
        },
        {
          "name": "드론",
          "line": "하던 이야기로 돌아갈까요?"
        },
        {
          "name": "주인공",
          "line": "요점만 말해."
        },
        {
          "name": "드론",
          "line": "의뢰 전단지를 돌린 사람 위치를 특정할 수 있습니다."
        },
        {
          "name": "",
          "line": ""
        },
        {
          "name": "",
          "line": ""
        },
        {
          "name": "",
          "line": ""
        },
        {
          "name": "",
          "line": ""
        },
        {
          "name": "",
          "line": ""
        },
        {
          "name": "",
          "line": ""
        },
        {
          "name": "",
          "line": ""
        },
        {
          "name": "",
          "line": ""
        },
        {
          "name": "",
          "line": ""
        },
        {
          "name": "",
          "line": ""
        },
        {
          "name": "",
          "line": ""
        }
      ]

    }
  ]
}