{
    "mapData": [
        {
            "moveDots": [
                {
                    "v3": {
                        "x": 0.0,
                        "y": 0.0,
                        "z": 0.0
                    },
                    "speed": 3.0
                },
                {
                    "v3": {
                        "x": 4.0,
                        "y": 0.0,
                        "z": 0.0
                    },
                    "speed": 3.0
                },
                {
                    "v3": {
                        "x": 8.0,
                        "y": 0.0,
                        "z": 0.0
                    },
                    "speed": 3.0
                },
                {
                    "v3": {
                        "x": 17.0,
                        "y": 0.0,
                        "z": 0.0
                    },
                    "speed": 3.0
                },
                {
                    "v3": {
                        "x": 22.0,
                        "y": 0.0,
                        "z": 0.0
                    },
                    "speed": 3.0
                },
                {
                    "v3": {
                        "x": 30.0,
                        "y": 0.0,
                        "z": 0.0
                    },
                    "speed": 3.0
                },
                {
                    "v3": {
                        "x": 32.0,
                        "y": 2.0,
                        "z": 0.0
                    },
                    "speed": 3.0
                },
                {
                    "v3": {
                        "x": 50.0,
                        "y": 2.0,
                        "z": 0.0
                    },
                    "speed": 3.0
                },
                {
                    "v3": {
                        "x": 70.0,
                        "y": 2.0,
                        "z": 0.0
                    },
                    "speed": 3.0
                },
                {
                    "v3": {
                        "x": 80.0,
                        "y": 1.0,
                        "z": 0.0
                    },
                    "speed": 3.0
                },
                {
                    "v3": {
                        "x": 83.0,
                        "y": 1.0,
                        "z": 0.0
                    },
                    "speed": 3.0
                },
                {
                    "v3": {
                        "x": 90.0,
                        "y": 4.0,
                        "z": 0.0
                    },
                    "speed": 3.0
                },
                {
                    "v3": {
                        "x": 93.20999908447266,
                        "y": 2.869999885559082,
                        "z": 0.0
                    },
                    "speed": 3.0
                },
                {
                    "v3": {
                        "x": 77.13999938964844,
                        "y": 19.860000610351564,
                        "z": 0.0
                    },
                    "speed": 3.0
                },
                {
                    "v3": {
                        "x": 63.150001525878909,
                        "y": 12.899999618530274,
                        "z": 0.0
                    },
                    "speed": 3.0
                },
                {
                    "v3": {
                        "x": 49.9900016784668,
                        "y": 18.079999923706056,
                        "z": 0.0
                    },
                    "speed": 3.0
                },
                {
                    "v3": {
                        "x": 65.68000030517578,
                        "y": 23.540000915527345,
                        "z": 0.0
                    },
                    "speed": 3.0
                },
                {
                    "v3": {
                        "x": 71.45999908447266,
                        "y": 20.65999984741211,
                        "z": 0.0
                    },
                    "speed": 3.0
                }
            ],
            "enemys": [
                {
                    "v3": {
                        "x": 4.0,
                        "y": 0.0,
                        "z": 0.0
                    },
                    "type": 0
                },
                {
                    "v3": {
                        "x": 11.0,
                        "y": 0.0,
                        "z": 0.0
                    },
                    "type": 1
                },
                {
                    "v3": {
                        "x": 16.0,
                        "y": 0.0,
                        "z": 0.0
                    },
                    "type": 0
                },
                {
                    "v3": {
                        "x": 20.0,
                        "y": 0.0,
                        "z": 0.0
                    },
                    "type": 0
                },
                {
                    "v3": {
                        "x": 48.0,
                        "y": 2.0,
                        "z": 0.0
                    },
                    "type": 0
                },
                {
                    "v3": {
                        "x": 39.77000045776367,
                        "y": 2.0199999809265138,
                        "z": 0.0
                    },
                    "type": 0
                },
                {
                    "v3": {
                        "x": 75.31999969482422,
                        "y": 19.0,
                        "z": 0.0
                    },
                    "type": 0
                },
                {
                    "v3": {
                        "x": 85.01799774169922,
                        "y": 11.562000274658204,
                        "z": 0.0
                    },
                    "type": 0
                },
                {
                    "v3": {
                        "x": 87.83000183105469,
                        "y": 8.619999885559082,
                        "z": 0.0
                    },
                    "type": 1
                },
                {
                    "v3": {
                        "x": 27.459999084472658,
                        "y": 0.03999999910593033,
                        "z": 0.0
                    },
                    "type": 1
                }
            ],
            "eventDots": [
                {
                    "v3": {
                        "x": 4.0,
                        "y": 0.0,
                        "z": 0.0
                    },
                    "type": 1,
                    "eventTypeInfo": {
                        "type0": {
                            "pointDot1": {
                                "x": 0.0,
                                "y": 0.0,
                                "z": 0.0
                            },
                            "pointDot2": {
                                "x": 0.0,
                                "y": 0.0,
                                "z": 0.0
                            },
                            "nextMoveDot": 0,
                            "time": 0.0
                        },
                        "type1": {
                            "upSpeed": 2,
                            "changeTime": 1.0
                        },
                        "type2": {
                            "cutSceneNumber": 0
                        },
                        "type3": {
                            "speed": 0,
                            "index": 0,
                            "startDot": 0,
                            "endDot": 0
                        },
                        "type4": {
                            "soundName": ""
                        },
                        "type5": {
                            "cameraActionName": ""
                        },
                        "type6": {
                            "power": 0,
                            "speed": 0
                        },
                        "type7": {
                            "timeScale": 0.0
                        },
                        "type8": {
                            "animationName": ""
                        },
                        "type9": {
                            "stopTime": 2.0
                        }
                    }
                },
                {
                    "v3": {
                        "x": 5.349999904632568,
                        "y": 0.0,
                        "z": 0.0
                    },
                    "type": 1,
                    "eventTypeInfo": {
                        "type0": {
                            "pointDot1": {
                                "x": 0.0,
                                "y": 0.0,
                                "z": 0.0
                            },
                            "pointDot2": {
                                "x": 0.0,
                                "y": 0.0,
                                "z": 0.0
                            },
                            "nextMoveDot": 0,
                            "time": 0.0
                        },
                        "type1": {
                            "upSpeed": 2,
                            "changeTime": 1.0
                        },
                        "type2": {
                            "cutSceneNumber": 0
                        },
                        "type3": {
                            "speed": 0,
                            "index": 0,
                            "startDot": 0,
                            "endDot": 0
                        },
                        "type4": {
                            "soundName": ""
                        },
                        "type5": {
                            "cameraActionName": "ZoomInAction"
                        },
                        "type6": {
                            "power": 0,
                            "speed": 0
                        },
                        "type7": {
                            "timeScale": 0.0
                        },
                        "type8": {
                            "animationName": ""
                        },
                        "type9": {
                            "stopTime": 2.0
                        }
                    }
                },
                {
                    "v3": {
                        "x": 22.739999771118165,
                        "y": -0.009999999776482582,
                        "z": 0.0
                    },
                    "type": 1,
                    "eventTypeInfo": {
                        "type0": {
                            "pointDot1": {
                                "x": 0.0,
                                "y": 0.0,
                                "z": 0.0
                            },
                            "pointDot2": {
                                "x": 0.0,
                                "y": 0.0,
                                "z": 0.0
                            },
                            "nextMoveDot": 0,
                            "time": 0.0
                        },
                        "type1": {
                            "upSpeed": 2,
                            "changeTime": 1.0
                        },
                        "type2": {
                            "cutSceneNumber": 0
                        },
                        "type3": {
                            "speed": 0,
                            "index": 0,
                            "startDot": 0,
                            "endDot": 0
                        },
                        "type4": {
                            "soundName": ""
                        },
                        "type5": {
                            "cameraActionName": "ZoomOutAction"
                        },
                        "type6": {
                            "power": 0,
                            "speed": 0
                        },
                        "type7": {
                            "timeScale": 0.0
                        },
                        "type8": {
                            "animationName": ""
                        },
                        "type9": {
                            "stopTime": 2.0
                        }
                    }
                },
                {
                    "v3": {
                        "x": 13.0,
                        "y": 0.0,
                        "z": 0.0
                    },
                    "type": 2,
                    "eventTypeInfo": {
                        "type0": {
                            "pointDot1": {
                                "x": 0.0,
                                "y": 0.0,
                                "z": 0.0
                            },
                            "pointDot2": {
                                "x": 0.0,
                                "y": 0.0,
                                "z": 0.0
                            },
                            "nextMoveDot": 0,
                            "time": 0.0
                        },
                        "type1": {
                            "upSpeed": 0,
                            "changeTime": 0.0
                        },
                        "type2": {
                            "cutSceneNumber": 0
                        },
                        "type3": {
                            "speed": 0,
                            "index": 0,
                            "startDot": 0,
                            "endDot": 0
                        },
                        "type4": {
                            "soundName": ""
                        },
                        "type5": {
                            "cameraActionName": ""
                        },
                        "type6": {
                            "power": 0,
                            "speed": 0
                        },
                        "type7": {
                            "timeScale": 0.0
                        },
                        "type8": {
                            "animationName": ""
                        },
                        "type9": {
                            "stopTime": 0.0
                        }
                    }
                },
                {
                    "v3": {
                        "x": 20.0,
                        "y": 0.0,
                        "z": 0.0
                    },
                    "type": 1,
                    "eventTypeInfo": {
                        "type0": {
                            "pointDot1": {
                                "x": 0.0,
                                "y": 0.0,
                                "z": 0.0
                            },
                            "pointDot2": {
                                "x": 0.0,
                                "y": 0.0,
                                "z": 0.0
                            },
                            "nextMoveDot": 0,
                            "time": 0.0
                        },
                        "type1": {
                            "upSpeed": -1,
                            "changeTime": 1.0
                        },
                        "type2": {
                            "cutSceneNumber": 0
                        },
                        "type3": {
                            "speed": 0,
                            "index": 0,
                            "startDot": 0,
                            "endDot": 0
                        },
                        "type4": {
                            "soundName": ""
                        },
                        "type5": {
                            "cameraActionName": ""
                        },
                        "type6": {
                            "power": 0,
                            "speed": 0
                        },
                        "type7": {
                            "timeScale": 0.0
                        },
                        "type8": {
                            "animationName": ""
                        },
                        "type9": {
                            "stopTime": 0.0
                        }
                    }
                },
                {
                    "v3": {
                        "x": 35.0,
                        "y": 2.0,
                        "z": 0.0
                    },
                    "type": 3,
                    "eventTypeInfo": {
                        "type0": {
                            "pointDot1": {
                                "x": 0.0,
                                "y": 0.0,
                                "z": 0.0
                            },
                            "pointDot2": {
                                "x": 0.0,
                                "y": 0.0,
                                "z": 0.0
                            },
                            "nextMoveDot": 0,
                            "time": 0.0
                        },
                        "type1": {
                            "upSpeed": 0,
                            "changeTime": 0.0
                        },
                        "type2": {
                            "cutSceneNumber": 0
                        },
                        "type3": {
                            "speed": 3,
                            "index": 4,
                            "startDot": 7,
                            "endDot": 6
                        },
                        "type4": {
                            "soundName": ""
                        },
                        "type5": {
                            "cameraActionName": ""
                        },
                        "type6": {
                            "power": 0,
                            "speed": 0
                        },
                        "type7": {
                            "timeScale": 0.0
                        },
                        "type8": {
                            "animationName": ""
                        },
                        "type9": {
                            "stopTime": 0.0
                        }
                    }
                },
                {
                    "v3": {
                        "x": 37.0,
                        "y": 2.0,
                        "z": 0.0
                    },
                    "type": 6,
                    "eventTypeInfo": {
                        "type0": {
                            "pointDot1": {
                                "x": 0.0,
                                "y": 0.0,
                                "z": 0.0
                            },
                            "pointDot2": {
                                "x": 0.0,
                                "y": 0.0,
                                "z": 0.0
                            },
                            "nextMoveDot": 0,
                            "time": 0.0
                        },
                        "type1": {
                            "upSpeed": 0,
                            "changeTime": 0.0
                        },
                        "type2": {
                            "cutSceneNumber": 0
                        },
                        "type3": {
                            "speed": 3,
                            "index": 4,
                            "startDot": 7,
                            "endDot": 6
                        },
                        "type4": {
                            "soundName": ""
                        },
                        "type5": {
                            "cameraActionName": ""
                        },
                        "type6": {
                            "power": 1,
                            "speed": 20
                        },
                        "type7": {
                            "timeScale": 0.0
                        },
                        "type8": {
                            "animationName": ""
                        },
                        "type9": {
                            "stopTime": 0.0
                        }
                    }
                },
                {
                    "v3": {
                        "x": 41.0,
                        "y": 2.0,
                        "z": 0.0
                    },
                    "type": 7,
                    "eventTypeInfo": {
                        "type0": {
                            "pointDot1": {
                                "x": 0.0,
                                "y": 0.0,
                                "z": 0.0
                            },
                            "pointDot2": {
                                "x": 0.0,
                                "y": 0.0,
                                "z": 0.0
                            },
                            "nextMoveDot": 0,
                            "time": 0.0
                        },
                        "type1": {
                            "upSpeed": 0,
                            "changeTime": 0.0
                        },
                        "type2": {
                            "cutSceneNumber": 0
                        },
                        "type3": {
                            "speed": 3,
                            "index": 4,
                            "startDot": 7,
                            "endDot": 6
                        },
                        "type4": {
                            "soundName": ""
                        },
                        "type5": {
                            "cameraActionName": ""
                        },
                        "type6": {
                            "power": 1,
                            "speed": 20
                        },
                        "type7": {
                            "timeScale": 0.5
                        },
                        "type8": {
                            "animationName": ""
                        },
                        "type9": {
                            "stopTime": 0.0
                        }
                    }
                },
                {
                    "v3": {
                        "x": 43.0,
                        "y": 2.0,
                        "z": 0.0
                    },
                    "type": 7,
                    "eventTypeInfo": {
                        "type0": {
                            "pointDot1": {
                                "x": 0.0,
                                "y": 0.0,
                                "z": 0.0
                            },
                            "pointDot2": {
                                "x": 0.0,
                                "y": 0.0,
                                "z": 0.0
                            },
                            "nextMoveDot": 0,
                            "time": 0.0
                        },
                        "type1": {
                            "upSpeed": 0,
                            "changeTime": 0.0
                        },
                        "type2": {
                            "cutSceneNumber": 0
                        },
                        "type3": {
                            "speed": 3,
                            "index": 4,
                            "startDot": 7,
                            "endDot": 6
                        },
                        "type4": {
                            "soundName": ""
                        },
                        "type5": {
                            "cameraActionName": ""
                        },
                        "type6": {
                            "power": 1,
                            "speed": 20
                        },
                        "type7": {
                            "timeScale": 1.0
                        },
                        "type8": {
                            "animationName": ""
                        },
                        "type9": {
                            "stopTime": 0.0
                        }
                    }
                },
                {
                    "v3": {
                        "x": 45.0,
                        "y": 2.0,
                        "z": 0.0
                    },
                    "type": 9,
                    "eventTypeInfo": {
                        "type0": {
                            "pointDot1": {
                                "x": 0.0,
                                "y": 0.0,
                                "z": 0.0
                            },
                            "pointDot2": {
                                "x": 0.0,
                                "y": 0.0,
                                "z": 0.0
                            },
                            "nextMoveDot": 0,
                            "time": 0.0
                        },
                        "type1": {
                            "upSpeed": 0,
                            "changeTime": 0.0
                        },
                        "type2": {
                            "cutSceneNumber": 0
                        },
                        "type3": {
                            "speed": 3,
                            "index": 4,
                            "startDot": 7,
                            "endDot": 6
                        },
                        "type4": {
                            "soundName": ""
                        },
                        "type5": {
                            "cameraActionName": ""
                        },
                        "type6": {
                            "power": 1,
                            "speed": 20
                        },
                        "type7": {
                            "timeScale": 1.0
                        },
                        "type8": {
                            "animationName": ""
                        },
                        "type9": {
                            "stopTime": 2.0
                        }
                    }
                },
                {
                    "v3": {
                        "x": 4.0,
                        "y": 0.0,
                        "z": 0.0
                    },
                    "type": 1,
                    "eventTypeInfo": {
                        "type0": {
                            "pointDot1": {
                                "x": 0.0,
                                "y": 0.0,
                                "z": 0.0
                            },
                            "pointDot2": {
                                "x": 0.0,
                                "y": 0.0,
                                "z": 0.0
                            },
                            "nextMoveDot": 0,
                            "time": 0.0
                        },
                        "type1": {
                            "upSpeed": 3,
                            "changeTime": 1.0
                        },
                        "type2": {
                            "cutSceneNumber": 0
                        },
                        "type3": {
                            "speed": 0,
                            "index": 0,
                            "startDot": 0,
                            "endDot": 0
                        },
                        "type4": {
                            "soundName": ""
                        },
                        "type5": {
                            "cameraActionName": ""
                        },
                        "type6": {
                            "power": 0,
                            "speed": 0
                        },
                        "type7": {
                            "timeScale": 0.0
                        },
                        "type8": {
                            "animationName": ""
                        },
                        "type9": {
                            "stopTime": 0.0
                        }
                    }
                },
                {
                    "v3": {
                        "x": 13.0,
                        "y": 0.0,
                        "z": 0.0
                    },
                    "type": 2,
                    "eventTypeInfo": {
                        "type0": {
                            "pointDot1": {
                                "x": 0.0,
                                "y": 0.0,
                                "z": 0.0
                            },
                            "pointDot2": {
                                "x": 0.0,
                                "y": 0.0,
                                "z": 0.0
                            },
                            "nextMoveDot": 0,
                            "time": 0.0
                        },
                        "type1": {
                            "upSpeed": 0,
                            "changeTime": 0.0
                        },
                        "type2": {
                            "cutSceneNumber": 0
                        },
                        "type3": {
                            "speed": 0,
                            "index": 0,
                            "startDot": 0,
                            "endDot": 0
                        },
                        "type4": {
                            "soundName": ""
                        },
                        "type5": {
                            "cameraActionName": ""
                        },
                        "type6": {
                            "power": 0,
                            "speed": 0
                        },
                        "type7": {
                            "timeScale": 0.0
                        },
                        "type8": {
                            "animationName": ""
                        },
                        "type9": {
                            "stopTime": 0.0
                        }
                    }
                },
                {
                    "v3": {
                        "x": 20.0,
                        "y": 0.0,
                        "z": 0.0
                    },
                    "type": 1,
                    "eventTypeInfo": {
                        "type0": {
                            "pointDot1": {
                                "x": 0.0,
                                "y": 0.0,
                                "z": 0.0
                            },
                            "pointDot2": {
                                "x": 0.0,
                                "y": 0.0,
                                "z": 0.0
                            },
                            "nextMoveDot": 0,
                            "time": 0.0
                        },
                        "type1": {
                            "upSpeed": -1,
                            "changeTime": 1.0
                        },
                        "type2": {
                            "cutSceneNumber": 0
                        },
                        "type3": {
                            "speed": 0,
                            "index": 0,
                            "startDot": 0,
                            "endDot": 0
                        },
                        "type4": {
                            "soundName": ""
                        },
                        "type5": {
                            "cameraActionName": ""
                        },
                        "type6": {
                            "power": 0,
                            "speed": 0
                        },
                        "type7": {
                            "timeScale": 0.0
                        },
                        "type8": {
                            "animationName": ""
                        },
                        "type9": {
                            "stopTime": 0.0
                        }
                    }
                },
                {
                    "v3": {
                        "x": 35.0,
                        "y": 2.0,
                        "z": 0.0
                    },
                    "type": 3,
                    "eventTypeInfo": {
                        "type0": {
                            "pointDot1": {
                                "x": 0.0,
                                "y": 0.0,
                                "z": 0.0
                            },
                            "pointDot2": {
                                "x": 0.0,
                                "y": 0.0,
                                "z": 0.0
                            },
                            "nextMoveDot": 0,
                            "time": 0.0
                        },
                        "type1": {
                            "upSpeed": 0,
                            "changeTime": 0.0
                        },
                        "type2": {
                            "cutSceneNumber": 0
                        },
                        "type3": {
                            "speed": 3,
                            "index": 4,
                            "startDot": 7,
                            "endDot": 6
                        },
                        "type4": {
                            "soundName": ""
                        },
                        "type5": {
                            "cameraActionName": ""
                        },
                        "type6": {
                            "power": 0,
                            "speed": 0
                        },
                        "type7": {
                            "timeScale": 0.0
                        },
                        "type8": {
                            "animationName": ""
                        },
                        "type9": {
                            "stopTime": 0.0
                        }
                    }
                },
                {
                    "v3": {
                        "x": 37.0,
                        "y": 2.0,
                        "z": 0.0
                    },
                    "type": 6,
                    "eventTypeInfo": {
                        "type0": {
                            "pointDot1": {
                                "x": 0.0,
                                "y": 0.0,
                                "z": 0.0
                            },
                            "pointDot2": {
                                "x": 0.0,
                                "y": 0.0,
                                "z": 0.0
                            },
                            "nextMoveDot": 0,
                            "time": 0.0
                        },
                        "type1": {
                            "upSpeed": 0,
                            "changeTime": 0.0
                        },
                        "type2": {
                            "cutSceneNumber": 0
                        },
                        "type3": {
                            "speed": 3,
                            "index": 4,
                            "startDot": 7,
                            "endDot": 6
                        },
                        "type4": {
                            "soundName": ""
                        },
                        "type5": {
                            "cameraActionName": ""
                        },
                        "type6": {
                            "power": 1,
                            "speed": 20
                        },
                        "type7": {
                            "timeScale": 0.0
                        },
                        "type8": {
                            "animationName": ""
                        },
                        "type9": {
                            "stopTime": 0.0
                        }
                    }
                },
                {
                    "v3": {
                        "x": 41.0,
                        "y": 2.0,
                        "z": 0.0
                    },
                    "type": 7,
                    "eventTypeInfo": {
                        "type0": {
                            "pointDot1": {
                                "x": 0.0,
                                "y": 0.0,
                                "z": 0.0
                            },
                            "pointDot2": {
                                "x": 0.0,
                                "y": 0.0,
                                "z": 0.0
                            },
                            "nextMoveDot": 0,
                            "time": 0.0
                        },
                        "type1": {
                            "upSpeed": 0,
                            "changeTime": 0.0
                        },
                        "type2": {
                            "cutSceneNumber": 0
                        },
                        "type3": {
                            "speed": 3,
                            "index": 4,
                            "startDot": 7,
                            "endDot": 6
                        },
                        "type4": {
                            "soundName": ""
                        },
                        "type5": {
                            "cameraActionName": ""
                        },
                        "type6": {
                            "power": 1,
                            "speed": 20
                        },
                        "type7": {
                            "timeScale": 0.5
                        },
                        "type8": {
                            "animationName": ""
                        },
                        "type9": {
                            "stopTime": 0.0
                        }
                    }
                },
                {
                    "v3": {
                        "x": 43.0,
                        "y": 2.0,
                        "z": 0.0
                    },
                    "type": 7,
                    "eventTypeInfo": {
                        "type0": {
                            "pointDot1": {
                                "x": 0.0,
                                "y": 0.0,
                                "z": 0.0
                            },
                            "pointDot2": {
                                "x": 0.0,
                                "y": 0.0,
                                "z": 0.0
                            },
                            "nextMoveDot": 0,
                            "time": 0.0
                        },
                        "type1": {
                            "upSpeed": 0,
                            "changeTime": 0.0
                        },
                        "type2": {
                            "cutSceneNumber": 0
                        },
                        "type3": {
                            "speed": 3,
                            "index": 4,
                            "startDot": 7,
                            "endDot": 6
                        },
                        "type4": {
                            "soundName": ""
                        },
                        "type5": {
                            "cameraActionName": ""
                        },
                        "type6": {
                            "power": 1,
                            "speed": 20
                        },
                        "type7": {
                            "timeScale": 1.0
                        },
                        "type8": {
                            "animationName": ""
                        },
                        "type9": {
                            "stopTime": 0.0
                        }
                    }
                },
                {
                    "v3": {
                        "x": 45.0,
                        "y": 2.0,
                        "z": 0.0
                    },
                    "type": 9,
                    "eventTypeInfo": {
                        "type0": {
                            "pointDot1": {
                                "x": 0.0,
                                "y": 0.0,
                                "z": 0.0
                            },
                            "pointDot2": {
                                "x": 0.0,
                                "y": 0.0,
                                "z": 0.0
                            },
                            "nextMoveDot": 0,
                            "time": 0.0
                        },
                        "type1": {
                            "upSpeed": 0,
                            "changeTime": 0.0
                        },
                        "type2": {
                            "cutSceneNumber": 0
                        },
                        "type3": {
                            "speed": 3,
                            "index": 4,
                            "startDot": 7,
                            "endDot": 6
                        },
                        "type4": {
                            "soundName": ""
                        },
                        "type5": {
                            "cameraActionName": ""
                        },
                        "type6": {
                            "power": 1,
                            "speed": 20
                        },
                        "type7": {
                            "timeScale": 1.0
                        },
                        "type8": {
                            "animationName": ""
                        },
                        "type9": {
                            "stopTime": 2.0
                        }
                    }
                },
                {
                    "v3": {
                        "x": 70.0,
                        "y": 2.0,
                        "z": 0.0
                    },
                    "type": 0,
                    "eventTypeInfo": {
                        "type0": {
                            "pointDot1": {
                                "x": 70.0,
                                "y": 4.0,
                                "z": 0.0
                            },
                            "pointDot2": {
                                "x": 80.0,
                                "y": 5.0,
                                "z": 0.0
                            },
                            "nextMoveDot": 9,
                            "time": 3.0
                        },
                        "type1": {
                            "upSpeed": 0,
                            "changeTime": 0.0
                        },
                        "type2": {
                            "cutSceneNumber": 0
                        },
                        "type3": {
                            "speed": 3,
                            "index": 4,
                            "startDot": 7,
                            "endDot": 6
                        },
                        "type4": {
                            "soundName": ""
                        },
                        "type5": {
                            "cameraActionName": ""
                        },
                        "type6": {
                            "power": 1,
                            "speed": 20
                        },
                        "type7": {
                            "timeScale": 1.0
                        },
                        "type8": {
                            "animationName": ""
                        },
                        "type9": {
                            "stopTime": 2.0
                        }
                    }
                },
                {
                    "v3": {
                        "x": 83.0,
                        "y": 1.0,
                        "z": 0.0
                    },
                    "type": 0,
                    "eventTypeInfo": {
                        "type0": {
                            "pointDot1": {
                                "x": 83.0,
                                "y": 4.0,
                                "z": 0.0
                            },
                            "pointDot2": {
                                "x": 90.0,
                                "y": 7.0,
                                "z": 0.0
                            },
                            "nextMoveDot": 11,
                            "time": 2.0
                        },
                        "type1": {
                            "upSpeed": 0,
                            "changeTime": 0.0
                        },
                        "type2": {
                            "cutSceneNumber": 0
                        },
                        "type3": {
                            "speed": 3,
                            "index": 4,
                            "startDot": 7,
                            "endDot": 6
                        },
                        "type4": {
                            "soundName": ""
                        },
                        "type5": {
                            "cameraActionName": ""
                        },
                        "type6": {
                            "power": 1,
                            "speed": 20
                        },
                        "type7": {
                            "timeScale": 1.0
                        },
                        "type8": {
                            "animationName": ""
                        },
                        "type9": {
                            "stopTime": 2.0
                        }
                    }
                },
                {
                    "v3": {
                        "x": 23.889999389648439,
                        "y": 0.0,
                        "z": 0.0
                    },
                    "type": 1,
                    "eventTypeInfo": {
                        "type0": {
                            "pointDot1": {
                                "x": 83.0,
                                "y": 4.0,
                                "z": 0.0
                            },
                            "pointDot2": {
                                "x": 90.0,
                                "y": 7.0,
                                "z": 0.0
                            },
                            "nextMoveDot": 11,
                            "time": 2.0
                        },
                        "type1": {
                            "upSpeed": 2,
                            "changeTime": 2.0
                        },
                        "type2": {
                            "cutSceneNumber": 0
                        },
                        "type3": {
                            "speed": 3,
                            "index": 4,
                            "startDot": 7,
                            "endDot": 6
                        },
                        "type4": {
                            "soundName": ""
                        },
                        "type5": {
                            "cameraActionName": ""
                        },
                        "type6": {
                            "power": 2,
                            "speed": 30
                        },
                        "type7": {
                            "timeScale": 1.0
                        },
                        "type8": {
                            "animationName": ""
                        },
                        "type9": {
                            "stopTime": 2.0
                        }
                    }
                },
                {
                    "v3": {
                        "x": 2.2200000286102297,
                        "y": -0.009999999776482582,
                        "z": 0.0
                    },
                    "type": 5,
                    "eventTypeInfo": {
                        "type0": {
                            "pointDot1": {
                                "x": 83.0,
                                "y": 4.0,
                                "z": 0.0
                            },
                            "pointDot2": {
                                "x": 90.0,
                                "y": 7.0,
                                "z": 0.0
                            },
                            "nextMoveDot": 11,
                            "time": 2.0
                        },
                        "type1": {
                            "upSpeed": 2,
                            "changeTime": 2.0
                        },
                        "type2": {
                            "cutSceneNumber": 0
                        },
                        "type3": {
                            "speed": 3,
                            "index": 4,
                            "startDot": 7,
                            "endDot": 6
                        },
                        "type4": {
                            "soundName": ""
                        },
                        "type5": {
                            "cameraActionName": "ShakeAction"
                        },
                        "type6": {
                            "power": 2,
                            "speed": 30
                        },
                        "type7": {
                            "timeScale": 1.0
                        },
                        "type8": {
                            "animationName": ""
                        },
                        "type9": {
                            "stopTime": 2.0
                        }
                    }
                },
                {
                    "v3": {
                        "x": 24.81999969482422,
                        "y": 0.009999999776482582,
                        "z": 0.0
                    },
                    "type": 5,
                    "eventTypeInfo": {
                        "type0": {
                            "pointDot1": {
                                "x": 83.0,
                                "y": 4.0,
                                "z": 0.0
                            },
                            "pointDot2": {
                                "x": 90.0,
                                "y": 7.0,
                                "z": 0.0
                            },
                            "nextMoveDot": 11,
                            "time": 2.0
                        },
                        "type1": {
                            "upSpeed": 2,
                            "changeTime": 2.0
                        },
                        "type2": {
                            "cutSceneNumber": 0
                        },
                        "type3": {
                            "speed": 3,
                            "index": 4,
                            "startDot": 7,
                            "endDot": 6
                        },
                        "type4": {
                            "soundName": ""
                        },
                        "type5": {
                            "cameraActionName": "ZoomOutAction"
                        },
                        "type6": {
                            "power": 2,
                            "speed": 30
                        },
                        "type7": {
                            "timeScale": 1.0
                        },
                        "type8": {
                            "animationName": ""
                        },
                        "type9": {
                            "stopTime": 2.0
                        }
                    }
                }
            ]
        },
        {
            "moveDots": [
                {
                    "v3": {
                        "x": 0.0,
                        "y": 0.0,
                        "z": 0.0
                    },
                    "speed": 3.0
                },
                {
                    "v3": {
                        "x": 1.0,
                        "y": 0.0,
                        "z": 0.0
                    },
                    "speed": 3.0
                },
                {
                    "v3": {
                        "x": 4.0,
                        "y": 0.0,
                        "z": 0.0
                    },
                    "speed": 8.0
                },
                {
                    "v3": {
                        "x": 8.0,
                        "y": 0.0,
                        "z": 0.0
                    },
                    "speed": 8.0
                },
                {
                    "v3": {
                        "x": 39.29999923706055,
                        "y": 10.199999809265137,
                        "z": 0.0
                    },
                    "speed": 8.0
                },
                {
                    "v3": {
                        "x": 38.79999923706055,
                        "y": 20.799999237060548,
                        "z": 0.0
                    },
                    "speed": 8.0
                },
                {
                    "v3": {
                        "x": 2.799999952316284,
                        "y": 21.100000381469728,
                        "z": 0.0
                    },
                    "speed": 8.0
                }
            ],
            "enemys": [
                {
                    "v3": {
                        "x": 3.0,
                        "y": 0.0,
                        "z": 0.0
                    },
                    "type": 0
                }
            ],
            "eventDots": []
        }
    ],
    "gameData": {
        "stage": 0,
        "stageClearInfo": [
            false,
            false,
            false,
            false,
            false
        ],
        "player": {
            "instanceID": 19874
        },
        "blood": {
            "instanceID": 20012
        },
        "bloodBoom": {
            "instanceID": 20014
        },
        "map": {
            "instanceID": 19818
        },
        "enemyInfo": [
            {
                "enemy": {
                    "instanceID": -8000
                },
                "x": 4.0,
                "index": 0
            },
            {
                "enemy": {
                    "instanceID": -8010
                },
                "x": 11.0,
                "index": 1
            },
            {
                "enemy": {
                    "instanceID": -8020
                },
                "x": 16.0,
                "index": 2
            },
            {
                "enemy": {
                    "instanceID": -8030
                },
                "x": 20.0,
                "index": 3
            },
            {
                "enemy": {
                    "instanceID": -8040
                },
                "x": 48.0,
                "index": 4
            },
            {
                "enemy": {
                    "instanceID": -8050
                },
                "x": 39.77000045776367,
                "index": 5
            },
            {
                "enemy": {
                    "instanceID": -8060
                },
                "x": 75.31999969482422,
                "index": 6
            },
            {
                "enemy": {
                    "instanceID": -8070
                },
                "x": 85.01799774169922,
                "index": 7
            },
            {
                "enemy": {
                    "instanceID": -8080
                },
                "x": 87.83000183105469,
                "index": 8
            },
            {
                "enemy": {
                    "instanceID": -8090
                },
                "x": 27.459999084472658,
                "index": 9
            }
        ],
        "camsize": 5.0
    },
    "ui": {
        "bgm": -40.0,
        "sfx": -40.0
    }
}